boyer/__init__.py
boyer/_boyer.py
boyer-0.1.7.dist-info/METADATA
boyer-0.1.7.dist-info/WHEEL
boyer-0.1.7.dist-info/top_level.txt
boyer-0.1.7.dist-info/RECORD
