Metadata-Version: 2.1
Name: boyer
Version: 0.1.7
Summary: Andrew Boyer's personal python library
Home-page: https://github.com/asboyer/boyer
Author: Andrew Boyer
Author-email: asboyer@gmail.com
License: MIT
Keywords: boyer
Platform: UNKNOWN
Requires-Python: >=3.5
